<QApairs id='1'>
<question>
Who	is	the	author	of	the	book	,	``	The	Iron	Lady	:	A	Biography	of	Margaret	Thatcher	''	?
NNP	VBZ	DT	NN	IN	DT	NN	,	``	DT	JJ	NN	:	DT	NN	IN	NNP	NNP	''	.
SUB	ROOT	NMOD	PRD	NMOD	NMOD	PMOD	P	P	NMOD	NMOD	NMOD	P	NMOD	NMOD	NMOD	NMOD	PMOD	P	P
2	0	4	2	4	7	5	15	15	12	12	15	15	15	7	15	18	16	18	2
-	-	-	PER_DESC-B	-	-	-	-	-	WORK_OF_ART-B	WORK_OF_ART-I	WORK_OF_ART-I	WORK_OF_ART-I	WORK_OF_ART-I	WORK_OF_ART-I	-	PERSON-B	PERSON-I	-	-
</question>
<positive>
the	IRON	LADY	;	A	Biography	of	Margaret	Thatcher	by	Hugo	Young	-LRB-	Farrar	,	Straus	&	Giroux	-RRB-
DT	NNP	NNP	:	DT	NN	IN	NNP	NNP	IN	NNP	NNP	-LRB-	NNP	,	NNP	CC	NNP	-RRB-
NMOD	NMOD	NMOD	P	NMOD	ROOT	NMOD	NMOD	PMOD	NMOD	NMOD	PMOD	P	NMOD	P	NMOD	NMOD	PMOD	P
3	3	6	6	6	0	6	9	7	6	12	10	18	18	18	18	18	10	18
-	ORGANIZATION-B	ORGANIZATION-I	ORGANIZATION-I	ORGANIZATION-I	ORGANIZATION-I	-	PERSON-B	PERSON-I	-	PERSON-B	PERSON-I	-	ORGANIZATION-B	ORGANIZATION-I	ORGANIZATION-I	ORGANIZATION-I	ORGANIZATION-I	-
Young	
12	
</positive>
<positive>
in	this	same	revisionist	mold	,	Hugo	Young	,	the	distinguished	British	journalist	,	has	performed	a	brilliant	dissection	of	the	notion	of	Thatcher	as	a	conservative	icon	.
IN	DT	JJ	NN	NN	,	NNP	NNP	,	DT	JJ	JJ	NN	,	VBZ	VBN	DT	JJ	NN	IN	DT	NN	IN	NNP	IN	DT	JJ	NN	.
VMOD	NMOD	NMOD	NMOD	PMOD	P	NMOD	NMOD	P	NMOD	NMOD	NMOD	SUB	P	ROOT	VC	NMOD	NMOD	OBJ	NMOD	NMOD	PMOD	NMOD	PMOD	VMOD	NMOD	NMOD	PMOD	P
15	5	5	5	1	15	8	13	13	13	13	13	15	15	0	15	19	19	16	19	22	20	22	23	16	28	28	25	15
-	-	-	-	-	-	PERSON-B	PERSON-I	-	-	-	NATIONALITY-B	PER_DESC-B	-	-	-	-	-	-	-	-	-	-	PERSON-B	-	-	-	-	-
Young	
8	
</positive>
<positive>
in	``	The	Iron	Lady	,	''	Young	traces	the	winding	staircase	of	fortune	that	transformed	the	younger	daughter	of	a	provincial	English	grocer	into	the	greatest	woman	political	leader	since	Catherine	the	Great	.
IN	``	DT	NNP	NNP	,	''	NNP	VBZ	DT	VBG	NN	IN	NN	WDT	VBD	DT	JJR	NN	IN	DT	JJ	JJ	NN	IN	DT	JJS	JJ	JJ	NN	IN	NNP	DT	NNP	.
VMOD	P	NMOD	NMOD	PMOD	P	P	SUB	ROOT	NMOD	NMOD	OBJ	NMOD	PMOD	NMOD	SBAR	NMOD	NMOD	OBJ	NMOD	NMOD	NMOD	NMOD	PMOD	VMOD	NMOD	NMOD	NMOD	NMOD	NMOD	NMOD	NMOD	NMOD	PMOD	P
9	1	5	5	1	9	9	9	0	12	12	9	12	13	12	15	19	19	16	19	24	24	24	20	16	30	30	30	30	34	30	34	34	25	9
-	-	-	PERSON-B	PERSON-I	-	-	ORGANIZATION-B	-	-	-	-	-	-	-	-	-	-	PER_DESC-B	-	-	-	NATIONALITY-B	-	-	-	-	PER_DESC-B	-	PER_DESC-B	-	PERSON-B	PERSON-I	PERSON-I	-
Young
8
</positive>
<positive>
``	He	is	the	very	essence	of	the	classless	meritocrat	,	''	says	Hugo	Young	,	Thatcher	's	biographer	.
``	PRP	VBZ	DT	RB	NN	IN	DT	NN	NN	,	''	VBZ	NNP	NNP	,	NNP	POS	NN	.
P	SUB	VMOD	NMOD	NMOD	PRD	NMOD	NMOD	NMOD	PMOD	P	P	ROOT	NMOD	NMOD	P	NMOD	NMOD	SUB	P
13	3	13	6	6	3	6	10	10	7	13	13	0	15	19	19	18	19	13	13
-	-	-	-	-	-	-	-	-	-	-	-	-	PERSON-B	PERSON-I	-	PERSON-B	-	PER_DESC-B	-
Young	
15	
</positive>
<negative>
From	her	father	,	Young	argues	,	she	inherited	a	``	joyless	earnestness	''	that	combined	with	her	early	interest	in	science	to	produce	the	roots	of	her	public	character	.
NNP	PRP$	NN	,	NNP	NNS	,	PRP	VBD	DT	``	JJ	NN	''	IN	VBD	IN	PRP$	JJ	NN	IN	NN	TO	VB	DT	NNS	IN	PRP$	JJ	NN	.
NMOD	NMOD	NMOD	P	NMOD	VMOD	P	SUB	ROOT	NMOD	P	NMOD	OBJ	P	NMOD	SBAR	VMOD	NMOD	NMOD	PMOD	NMOD	PMOD	VMOD	VMOD	NMOD	OBJ	NMOD	NMOD	NMOD	PMOD	P
6	6	6	6	6	9	9	9	0	13	13	13	9	13	13	15	16	20	20	17	20	21	24	16	26	24	26	30	30	27	9
-	-	PER_DESC-B	-	ORGANIZATION-B	-	-	-	-	-	-	-	-	-	-	-	-	-	-	-	-	-	-	-	-	-	-	-	-	PER_DESC-B	-
</negative>
<negative>
And	boys	they	were	,	teen-agers	too	young	for	the	exercise	of	informed	free	will	,	yet	sent	on	missions	to	Vietnam	that	many	would	later	consider	immoral	.
CC	NNS	PRP	VBD	,	NNS	RB	JJ	IN	DT	NN	IN	JJ	JJ	NN	,	VB	VBN	IN	NNS	TO	NNP	IN	JJ	MD	RB	VB	JJ	.
VMOD	VMOD	SUB	VMOD	P	SUB	AMOD	PRD	AMOD	NMOD	PMOD	NMOD	AMOD	NMOD	PMOD	P	ROOT	VC	VMOD	PMOD	VMOD	PMOD	VMOD	SUB	SBAR	VMOD	VC	VMOD	P
4	4	4	17	4	8	8	4	8	11	9	11	14	15	12	4	0	17	18	19	18	21	18	25	23	25	25	27	17
-	PER_DESC-B	-	-	-	PER_DESC-B	-	-	-	-	-	-	-	-	-	-	-	-	-	-	-	GPE-B	-	-	-	-	-	-	-
</negative>
<negative>
This	simple	,	powerful	,	engaging	prose	-LRB-	translated	from	the	Chinese	-RRB-	is	the	work	of	a	young	writer	who	at	16	was	sent	away	from	her	family	for	eight	years	to	a	poverty-stricken	northern	province	of	China	to	fulfill	the	Cultural	Revolutionary	requirement	of	intellectuals	.
DT	NN	,	JJ	,	VBG	NN	-LRB-	VBN	IN	DT	JJ	-RRB-	VBZ	DT	NN	IN	DT	JJ	NN	WP	IN	CD	VBD	VBN	RB	IN	PRP$	NN	IN	JJ	NNS	TO	DT	JJ	JJ	NN	IN	NNP	TO	VB	DT	JJ	NNP	NN	IN	NNS	.
NMOD	SUB	P	NMOD	P	NMOD	SUB	P	NMOD	VMOD	NMOD	PMOD	P	ROOT	NMOD	PRD	NMOD	NMOD	NMOD	PMOD	NMOD	VMOD	PMOD	SBAR	VC	VMOD	AMOD	NMOD	PMOD	VMOD	NMOD	PMOD	VMOD	NMOD	NMOD	NMOD	PMOD	NMOD	PMOD	VMOD	VMOD	NMOD	NMOD	NMOD	OBJ	NMOD	PMOD	P
2	14	14	7	7	7	14	9	7	9	12	10	9	0	16	14	16	20	20	17	20	24	22	21	24	25	26	29	27	25	32	30	25	37	37	37	33	37	38	41	25	45	45	45	41	45	46	14
-	-	-	-	-	-	-	-	-	-	-	NATIONALITY-B	-	-	-	-	-	-	-	PER_DESC-B	-	-	CARDINAL-B	-	-	-	-	-	PER_DESC-B	-	DATE-B	DATE-I	-	-	-	-	GPE_DESC-B	-	GPE-B	-	-	-	EVENT-B	EVENT-I	-	-	PER_DESC-B	-
</negative>
<negative>
To	read	Young	is	to	discover	that	certain	suspect	analogies	have	informed	the	American	perception	of	Thatcher	as	a	conservative	heroine	.
TO	VB	NNP	VBZ	TO	VB	IN	JJ	NN	NNS	VBP	VBN	DT	JJ	NN	IN	NNP	IN	DT	JJ	NN	.
VMOD	VMOD	SUB	ROOT	VMOD	VMOD	VMOD	NMOD	NMOD	SUB	SBAR	VC	NMOD	NMOD	OBJ	NMOD	PMOD	VMOD	NMOD	NMOD	PMOD	P
2	4	4	0	6	4	6	10	10	11	7	11	15	15	12	15	16	12	21	21	18	4
-	-	ORGANIZATION-B	-	-	-	-	-	PER_DESC-B	PER_DESC-I	-	-	-	NATIONALITY-B	-	-	PERSON-B	-	-	-	PER_DESC-B	-
</negative>
<negative>
Neither	the	assumption	that	Thatcher	's	road	to	Damascus	parallels	Ronald	Reagan	's	own	timely	evolution	from	New	Deal	enthusiast	to	conservative	idealogue	,	nor	the	thesis	that	the	Iron	Lady	took	the	Tory	party	by	storm	in	a	political	coup	a	la	Barry	Goldwater	,	survives	Young	's	analysis	.
RB	DT	NN	IN	NNP	POS	NN	TO	NNP	NNS	NNP	NNP	POS	JJ	JJ	NN	IN	NNP	NNP	NN	TO	JJ	NN	,	CC	DT	NN	IN	DT	NNP	NNP	VBD	DT	NN	NN	IN	NN	IN	DT	JJ	NN	DT	NN	RB	NNP	,	VBZ	NNP	POS	NN	.
NMOD	NMOD	NMOD	NMOD	NMOD	NMOD	SUB	NMOD	NMOD	PMOD	NMOD	NMOD	NMOD	NMOD	NMOD	PMOD	NMOD	NMOD	NMOD	PMOD	PMOD	NMOD	PMOD	P	VMOD	NMOD	SUB	NMOD	NMOD	NMOD	SUB	ROOT	NMOD	NMOD	OBJ	VMOD	PMOD	VMOD	NMOD	NMOD	PMOD	NMOD	NMOD	NMOD	PMOD	P	VMOD	NMOD	NMOD	OBJ	P
3	3	6	3	6	7	32	7	10	8	13	13	16	16	16	8	16	20	20	17	17	23	21	32	32	27	32	27	31	31	32	0	35	35	32	32	36	32	41	41	38	43	45	45	38	32	32	49	50	47	32
-	-	-	-	PERSON-B	-	FAC_DESC-B	-	GPE-B	-	PERSON-B	PERSON-I	-	-	-	-	-	-	-	PER_DESC-B	-	-	-	-	-	-	-	-	-	PERSON-B	PERSON-I	-	-	NATIONALITY-B	ORG_DESC-B	-	-	-	-	-	-	-	-	PERSON-B	PERSON-I	-	-	ORGANIZATION-B	-	-	-
</negative>
<negative>
Young	makes	a	persuasive	case	for	the	view	that	Thatcher	's	less-than-true-blue	ideology	was	mirrored	in	her	policies	.
NNP	VBZ	DT	JJ	NN	IN	DT	NN	IN	NNP	POS	JJ	NN	VBD	VBN	IN	PRP$	NNS	.
SUB	ROOT	NMOD	NMOD	OBJ	NMOD	NMOD	PMOD	NMOD	NMOD	NMOD	NMOD	SUB	SBAR	VC	VMOD	NMOD	PMOD	P
2	0	5	5	2	5	8	6	8	11	13	13	14	9	14	15	18	16	2
-	-	-	-	-	-	-	-	-	PERSON-B	-	-	-	-	-	-	-	-	-
</negative>
<negative>
The	Tory	campaign	manifesto	drawn	up	for	the	1979	election	that	made	Thatcher	prime	minister	,	in	Young	's	words	,	``	openly	contemplated	the	perpetuation	of	the	comfortable	welfare	state	.	''
DT	JJ	NN	NN	VBN	RP	IN	DT	CD	NN	WDT	VBD	RB	JJ	NN	,	IN	NNP	POS	NNS	,	``	RB	VBD	DT	NN	IN	DT	JJ	JJ	NN	.	''
NMOD	NMOD	NMOD	SUB	ROOT	VMOD	VMOD	NMOD	NMOD	PMOD	NMOD	SBAR	AMOD	NMOD	OBJ	P	VMOD	NMOD	NMOD	PMOD	P	P	VMOD	VMOD	NMOD	OBJ	NMOD	NMOD	NMOD	NMOD	PMOD	P	P
4	4	4	5	0	5	5	10	10	7	10	11	14	15	12	15	12	19	20	17	10	24	24	5	26	24	26	31	31	31	27	5	5
-	NATIONALITY-B	-	-	-	-	-	-	DATE-B	-	-	-	PERSON-B	PER_DESC-B	PER_DESC-I	-	-	ORGANIZATION-B	-	-	-	-	-	-	-	-	-	-	-	-	GPE_DESC-B	-	-
</negative>
<negative>
Young	observes	that	``	There	was	a	genuine	clash	of	cultures	,	between	an	almost	Cromwellian	impatience	with	the	status	quo	-LRB-	on	the	part	of	the	Thatcherites	-RRB-	and	the	mandarin	world	of	Whitehall	,	in	which	skepticism	and	rumination	were	more	highly	rated	habits	of	mind	than	zeal	or	blind	conviction	.	''
NNP	VBZ	IN	``	EX	VBD	DT	JJ	NN	IN	NNS	,	IN	DT	RB	JJ	NN	IN	DT	NN	NN	-LRB-	IN	DT	NN	IN	DT	NNPS	-RRB-	CC	DT	JJ	NN	IN	NNP	,	IN	WDT	VBP	CC	NN	VBD	RBR	RB	VBN	NNS	IN	NN	IN	NN	CC	NN	NN	.	''
SUB	ROOT	VMOD	P	SUB	SBAR	NMOD	NMOD	PRD	NMOD	PMOD	P	VMOD	NMOD	AMOD	NMOD	PMOD	NMOD	NMOD	NMOD	NMOD	P	NMOD	NMOD	PMOD	NMOD	NMOD	PMOD	P	NMOD	NMOD	NMOD	PMOD	NMOD	PMOD	P	NMOD	PMOD	SBAR	VMOD	SUB	SBAR	AMOD	AMOD	VC	OBJ	NMOD	PMOD	NMOD	NMOD	NMOD	NMOD	PMOD	P	P
2	0	2	3	6	3	9	9	6	9	10	6	6	17	16	17	13	17	21	21	33	23	21	25	23	25	28	26	23	33	33	33	18	33	34	35	35	37	37	42	42	37	44	45	42	45	46	47	46	53	53	53	49	2	2
-	-	-	-	-	-	-	-	-	-	-	-	-	-	-	-	-	-	-	-	-	-	-	-	-	-	-	ORGANIZATION-B	-	-	-	-	-	-	ORGANIZATION-B	-	-	-	-	-	-	-	-	-	-	-	-	-	-	-	-	-	-	-	-
</negative>
<negative>
Despite	Thatcher	's	own	ambition	to	go	``	on	and	on	,	''	Young	argues	that	in	fact	her	era	has	come	and	gone	.
NNP	NNP	POS	JJ	NN	TO	VB	``	RB	CC	RB	,	''	NNP	NNS	IN	IN	JJ	PRP$	NN	VBZ	VBN	CC	NN	.
NMOD	NMOD	NMOD	NMOD	SUB	VMOD	NMOD	P	VMOD	AMOD	AMOD	P	P	NMOD	SUB	NMOD	VMOD	VMOD	NMOD	SUB	ROOT	VC	NMOD	PRD	P
3	3	5	5	21	7	5	7	7	9	9	21	15	15	21	15	21	21	20	21	0	21	24	22	21
-	PERSON-B	-	-	-	-	-	-	-	-	-	-	-	ORGANIZATION-B	-	-	-	-	-	-	-	-	-	-	-
</negative>
<negative>
``	Normally	,	I	discourage	people	from	entering	politics	if	they	have	a	young	family	and	do	n't	have	money	,	''	Barber	said	on	Tuesday	.
``	RB	,	PRP	VBP	NNS	IN	VBG	NNS	IN	PRP	VBP	DT	JJ	NN	CC	VBP	RB	VB	NN	,	''	NNP	VBD	IN	NNP	.
P	VMOD	P	SUB	VMOD	OBJ	VMOD	PMOD	OBJ	VMOD	SUB	SBAR	NMOD	NMOD	OBJ	VMOD	VMOD	VMOD	VC	OBJ	P	P	SUB	ROOT	VMOD	PMOD	P
24	5	5	5	24	5	5	7	8	8	12	10	15	15	12	12	12	17	17	19	24	24	24	0	24	25	24
-	WORK_OF_ART-B	-	-	-	PER_DESC-B	-	-	-	-	-	-	-	-	PER_DESC-B	-	-	-	-	-	-	-	PERSON-B	-	-	DATE-B	-
</negative>
<negative>
Major	learned	his	politics	as	a	Young	Conservative	on	a	soapbox	in	Brixton	,	a	poor	,	racially	mixed	neighborhood	in	south	London	,	where	he	took	on	the	socialist	Labor	Party	for	its	inept	management	of	the	area	's	public	housing	projects	.
NNP	VBD	PRP$	NNS	IN	DT	JJ	NN	IN	DT	NN	IN	NNP	,	DT	NN	,	RB	JJ	NN	IN	JJ	NNP	,	WRB	PRP	VBD	IN	DT	NN	NNP	NNP	IN	PRP$	JJ	NN	IN	DT	NN	POS	JJ	NN	NNS	.
SUB	ROOT	NMOD	OBJ	VMOD	NMOD	NMOD	PMOD	NMOD	NMOD	PMOD	NMOD	NMOD	P	NMOD	NMOD	P	NMOD	NMOD	PMOD	NMOD	NMOD	PMOD	P	NMOD	SUB	SBAR	VMOD	NMOD	NMOD	NMOD	PMOD	VMOD	NMOD	NMOD	PMOD	NMOD	NMOD	NMOD	NMOD	NMOD	NMOD	PMOD	P
2	0	4	2	2	8	8	5	8	11	9	11	20	20	16	20	20	20	20	12	20	23	21	20	20	27	25	27	32	32	32	28	27	36	36	33	36	40	40	43	43	43	37	2
-	-	-	-	-	-	ORGANIZATION-B	ORGANIZATION-I	-	-	-	-	GPE-B	-	-	-	-	-	-	-	-	-	GPE-B	-	-	-	-	-	-	-	ORGANIZATION-B	ORGANIZATION-I	-	-	-	PER_DESC-B	-	-	-	-	-	-	-	-
</negative>
<negative>
BIOGRAPHY
NNP
ROOT
0
ORGANIZATION-B
</negative>
<negative>
This	second	volume	of	Ward	's	lively	and	psychologically	revealing	biography	begins	with	his	honeymoon	abroad	in	1905	and	concludes	with	his	election	as	Governor	of	New	York	in	1928	.
DT	JJ	NN	IN	NNP	POS	JJ	CC	RB	VBG	JJ	NNS	IN	PRP$	NN	RB	IN	CD	CC	NNS	IN	PRP$	NN	IN	NNP	IN	NNP	NNP	IN	CD	.
NMOD	NMOD	NMOD	NMOD	NMOD	NMOD	NMOD	NMOD	VMOD	NMOD	NMOD	NMOD	NMOD	NMOD	PMOD	NMOD	NMOD	PMOD	NMOD	PMOD	NMOD	NMOD	ROOT	NMOD	PMOD	NMOD	NMOD	PMOD	NMOD	PMOD	P
3	3	23	3	6	12	12	12	10	12	12	23	12	15	13	15	15	17	20	17	20	23	0	23	24	25	28	26	23	29	23
-	ORDINAL-B	-	-	PERSON-B	-	-	-	-	-	-	-	-	-	-	-	-	DATE-B	-	-	-	-	-	-	PER_DESC-B	-	GPE-B	GPE-I	-	DATE-B	-
</negative>
<negative>
The	central	riddle	revealed	here	is	why	,	as	a	woman	in	a	man	's	world	,	Margaret	Thatcher	evinces	such	an	exclusionary	attitude	toward	women	.
DT	JJ	NN	VBD	RB	VBZ	RB	,	IN	DT	NN	IN	DT	NN	POS	NN	,	NNP	NNP	NNS	PDT	DT	JJ	NN	NN	VBN	.
NMOD	NMOD	SUB	ROOT	VMOD	VMOD	PRD	P	VMOD	NMOD	PMOD	NMOD	NMOD	NMOD	NMOD	PMOD	P	NMOD	NMOD	NMOD	NMOD	NMOD	NMOD	NMOD	SUB	SBAR	P
3	3	4	0	4	4	6	6	6	11	9	11	15	15	16	12	26	20	20	25	25	25	25	25	26	9	4
-	-	ORG_DESC-B	-	-	-	-	-	-	-	PER_DESC-B	-	-	PER_DESC-B	-	-	-	PERSON-B	PERSON-I	-	-	-	-	-	-	PER_DESC-B	-
</negative>
<negative>
The	author	,	whose	career	as	a	political	columnist	has	coincided	with	Thatcher	's	as	political	leader	,	describes	two	qualities	that	are	her	greatest	strengths	:	her	``	sense	of	moral	rectitude	''	and	her	political	intuition	.
DT	NN	,	WP$	NN	IN	DT	JJ	NN	VBZ	VBN	IN	NNP	POS	JJ	JJ	NN	,	VBZ	CD	NNS	WDT	VBP	PRP$	JJS	NNS	:	PRP	``	NN	IN	JJ	NN	''	CC	PRP$	JJ	NN	.
NMOD	SUB	P	NMOD	NMOD	NMOD	NMOD	NMOD	PMOD	SBAR	VC	VMOD	NMOD	NMOD	NMOD	NMOD	PMOD	P	ROOT	NMOD	NMOD	NMOD	SBAR	NMOD	NMOD	NMOD	P	NMOD	P	NMOD	NMOD	NMOD	PMOD	P	NMOD	NMOD	NMOD	OBJ	P
2	19	2	2	4	4	9	9	6	6	10	11	14	17	17	17	12	2	0	21	38	21	22	26	26	38	38	30	30	38	30	33	31	38	38	38	38	19	19
-	PER_DESC-B	-	-	-	-	-	-	PER_DESC-B	-	-	-	PERSON-B	-	-	-	PER_DESC-B	-	-	CARDINAL-B	-	-	-	-	-	-	-	-	-	-	-	-	-	-	-	-	-	-	-
</negative>
<negative>
The	Pulitizer	Prize-winning	author	's	second	book	in	a	projected	four	-volume	work	on	the	life	of	one	of	our	most	complex	presidents	.
DT	NNP	NNP	NNP	POS	JJ	NN	IN	DT	JJ	CD	NN	NN	IN	DT	NN	IN	CD	IN	PRP$	RBS	JJ	NNS	.
NMOD	NMOD	NMOD	NMOD	NMOD	NMOD	ROOT	NMOD	NMOD	NMOD	NMOD	NMOD	PMOD	NMOD	NMOD	PMOD	NMOD	PMOD	NMOD	NMOD	AMOD	NMOD	PMOD	P
5	5	5	5	7	7	0	7	13	13	13	13	8	13	16	14	16	17	18	23	22	23	19	7
-	WORK_OF_ART-B	-	PER_DESC-B	-	ORDINAL-B	-	-	-	-	CARDINAL-B	-	-	-	-	-	-	CARDINAL-B	-	-	-	-	PER_DESC-B	-
</negative>
<negative>
The	author	,	a	former	investigative	journalist	,	was	able	to	elicit	untapped	recollections	from	Johnson	's	old	cronies	.
DT	NN	,	DT	JJ	NN	NN	,	VBD	JJ	TO	VB	JJ	NNS	IN	NNP	POS	JJ	NNS	.
NMOD	NMOD	P	NMOD	NMOD	NMOD	SUB	P	ROOT	PRD	VMOD	AMOD	NMOD	OBJ	VMOD	NMOD	NMOD	NMOD	PMOD	P
2	7	7	7	7	7	9	7	0	9	12	10	14	12	12	17	19	19	15	9
-	PER_DESC-B	-	-	-	-	PER_DESC-B	-	-	-	-	-	-	-	-	PERSON-B	-	-	PER_DESC-B	-
</negative>
<negative>
SIMONE	DE	BEAUVOIR	;	A	Biography	by	Deirdre	Bair	-LRB-	Summit	Books	-RRB-
NNP	NNP	NNP	:	DT	JJ	IN	NNP	NNP	-LRB-	NNP	NNP	-RRB-
NMOD	NMOD	NMOD	P	NMOD	ROOT	NMOD	NMOD	PMOD	P	NMOD	NMOD	P
3	3	6	6	6	0	6	9	7	12	12	9	12
ORGANIZATION-B	ORGANIZATION-I	ORGANIZATION-I	ORGANIZATION-I	ORGANIZATION-I	ORGANIZATION-I	-	PERSON-B	PERSON-I	-	ORGANIZATION-B	ORGANIZATION-I	-
</negative>
<negative>
It	took	the	author	,	recipient	of	the	National	Book	Award	for	her	biography	of	Samuel	Beckett	,	seven	years	to	answer	these	questions	.
PRP	VBD	DT	NN	,	NN	IN	DT	NNP	NNP	NNP	IN	PRP$	NN	IN	NNP	NNP	,	CD	NNS	TO	VB	DT	NNS	.
SUB	ROOT	NMOD	OBJ	P	OBJ	NMOD	NMOD	NMOD	NMOD	PMOD	VMOD	NMOD	PMOD	NMOD	NMOD	PMOD	P	NMOD	AMOD	VMOD	SBAR	NMOD	OBJ	P
2	0	4	2	2	2	6	11	11	11	7	2	14	12	14	17	15	22	20	21	22	12	24	22	2
-	-	-	PER_DESC-B	-	PER_DESC-B	-	-	WORK_OF_ART-B	WORK_OF_ART-I	WORK_OF_ART-I	-	-	-	-	PERSON-B	PERSON-I	-	DATE-B	DATE-I	-	-	-	-	-
</negative>
<negative>
As	a	member	of	the	white	master	tribe	of	South	Africa	,	the	author	grew	up	thinking	himself	a	``	Just	White	Man	.	''
IN	DT	NN	IN	DT	JJ	NN	NN	IN	NNP	NNP	,	DT	NN	VBN	RP	VBG	PRP	DT	``	NNP	NNP	NNP	.	''
VMOD	NMOD	NMOD	NMOD	NMOD	NMOD	NMOD	PMOD	NMOD	NMOD	PMOD	P	NMOD	SUB	ROOT	VMOD	VMOD	SUB	NMOD	P	NMOD	NMOD	VMOD	P	P
15	3	14	3	8	8	8	4	8	11	9	14	14	15	0	15	15	23	23	23	23	23	17	15	15
-	-	PER_DESC-B	-	-	-	PER_DESC-B	PER_DESC-I	-	GPE-B	GPE-I	-	-	PER_DESC-B	-	-	-	-	-	-	WORK_OF_ART-B	WORK_OF_ART-I	WORK_OF_ART-I	-	-
</negative>
<negative>
Boundary	lines	for	the	new	Middle	East	were	arbitrarily	drawn	on	``	an	empty	map	''	without	any	input	from	the	leaders	of	those	countries	themselves	,	says	the	author	of	this	carefully	researched	book	based	on	recently	opened	archival	material	.
NNP	NNS	IN	DT	JJ	JJ	NNP	VBD	RB	VBN	IN	``	DT	NN	NN	''	IN	DT	NN	IN	DT	NNS	IN	DT	NNS	RB	,	VBZ	DT	NN	IN	DT	RB	VBN	NN	VBN	IN	RB	VBN	JJ	NN	.
NMOD	SUB	NMOD	NMOD	NMOD	NMOD	PMOD	VMOD	VMOD	VC	VMOD	P	NMOD	NMOD	PMOD	P	VMOD	NMOD	PMOD	NMOD	NMOD	PMOD	NMOD	NMOD	PMOD	NMOD	P	ROOT	NMOD	SUB	NMOD	NMOD	AMOD	NMOD	PMOD	NMOD	PMOD	AMOD	NMOD	NMOD	PMOD	P
2	8	2	7	7	7	3	28	10	8	10	15	15	15	11	11	10	19	17	19	22	20	22	25	23	25	28	0	30	28	30	35	34	35	31	35	36	39	41	41	37	28
-	-	-	-	-	LOCATION-B	LOCATION-I	-	-	-	-	-	-	-	-	-	-	-	-	-	-	PER_DESC-B	-	-	GPE_DESC-B	-	-	-	-	PER_DESC-B	-	-	-	-	-	-	-	-	-	-	-	-
</negative>
<negative>
A	passionately	told	epic	of	China	by	Yale	professor	and	historian	Spence	,	author	of	eight	other	acclaimed	works	on	China	.
DT	RB	VBD	JJ	IN	NNP	IN	JJ	NN	CC	JJ	NN	,	NN	IN	JJ	JJ	JJ	NNS	IN	NNP	.
SUB	VMOD	ROOT	OBJ	AMOD	PMOD	VMOD	NMOD	NMOD	NMOD	NMOD	PMOD	P	PMOD	NMOD	NMOD	NMOD	NMOD	PMOD	NMOD	PMOD	P
3	3	0	3	4	5	3	9	12	12	12	7	14	7	14	19	19	19	15	19	20	3
-	-	-	-	-	GPE-B	-	ORGANIZATION-B	PER_DESC-B	-	PER_DESC-B	PERSON-B	-	-	-	CARDINAL-B	-	-	-	-	GPE-B	-
</negative>
<negative>
The	author	's	dilemma	was	where	to	begin	in	a	recorded	history	that	spans	4,000	years	.
DT	NN	POS	NN	VBD	WRB	TO	VB	IN	DT	JJ	NN	WDT	VBZ	CD	NNS	.
NMOD	NMOD	NMOD	SUB	ROOT	VMOD	VMOD	SBAR	VMOD	NMOD	NMOD	PMOD	NMOD	SBAR	NMOD	OBJ	P
3	3	4	5	0	5	8	6	8	12	12	9	12	13	16	14	5
-	PER_DESC-B	-	-	-	-	-	-	-	-	-	-	-	-	CARDINAL-B	DATE-B	-
</negative>
<negative>
There	are	two	aspects	of	the	Margaret	Thatcher	phenomenon	--	neither	of	which	is	addressed	in	this	splendid	British	biography	--	that	every	thinking	American	needs	to	keep	in	mind	when	assessing	the	achievements	of	this	remarkable	woman	.
EX	VBP	CD	NNS	IN	DT	NNP	NNP	NNP	:	NN	IN	WDT	VBZ	VBN	IN	DT	JJ	JJ	NN	:	IN	NN	VBG	JJ	NNS	TO	VB	IN	NN	WRB	VBG	DT	NNS	IN	DT	JJ	NN	.
SUB	ROOT	NMOD	PRD	NMOD	NMOD	NMOD	NMOD	PMOD	P	PMOD	NMOD	PMOD	SBAR	VC	VMOD	NMOD	NMOD	NMOD	PMOD	P	NMOD	SUB	NMOD	NMOD	OBJ	VMOD	VMOD	VMOD	PMOD	VMOD	SBAR	NMOD	OBJ	NMOD	NMOD	NMOD	PMOD	P
2	0	4	2	4	9	9	9	5	11	5	11	12	12	14	15	20	20	20	16	11	23	24	4	26	24	28	24	28	29	28	31	34	32	34	38	38	35	2
-	-	CARDINAL-B	-	-	-	PERSON-B	PERSON-I	-	-	-	-	-	-	-	-	-	-	NATIONALITY-B	-	-	-	-	-	ORGANIZATION-B	-	-	-	-	-	-	-	-	-	-	-	-	PER_DESC-B	-
</negative>
<negative>
In	ideological	terms	,	the	author	makes	it	clear	that	,	her	paternal	education	in	conservative	sentiment	aside	,	not	only	did	Thatcher	come	to	the	true	faith	much	later	than	Reagan	,	but	that	between	1959	-LRB-	when	she	first	entered	Parliament	-RRB-	and	her	crucial	battle	with	Edward	Heath	for	leadership	of	the	Tory	party	in	1974	,	Thatcher	had	barely	two	conservative	ideas	to	rub	together	.
IN	JJ	NNS	,	DT	NN	VBZ	PRP	JJ	WDT	,	PRP$	JJ	NN	IN	JJ	NN	NN	,	RB	RB	VBD	RB	VB	TO	DT	JJ	NN	JJ	RBR	IN	NNP	,	CC	IN	IN	CD	-LRB-	WRB	PRP	RB	JJ	NNP	-RRB-	CC	PRP$	JJ	NN	IN	NNP	NNP	IN	NN	IN	DT	JJ	NN	IN	CD	,	NNP	VBD	RB	CD	JJ	NNS	TO	VB	NN	.
VMOD	NMOD	PMOD	P	NMOD	SUB	ROOT	SUB	VMOD	VMOD	P	NMOD	NMOD	NMOD	NMOD	NMOD	NMOD	PMOD	P	VMOD	DEP	SBAR	VMOD	VC	VMOD	NMOD	NMOD	PMOD	NMOD	NMOD	AMOD	PMOD	P	DEP	NMOD	VMOD	AMOD	NMOD	NMOD	NMOD	AMOD	NMOD	NMOD	P	NMOD	NMOD	NMOD	PMOD	NMOD	NMOD	PMOD	NMOD	PMOD	NMOD	NMOD	NMOD	PMOD	NMOD	PMOD	P	SUB	SBAR	NMOD	NMOD	NMOD	OBJ	VMOD	VMOD	OBJ	P
7	3	1	7	6	7	0	9	7	7	10	14	14	20	14	18	18	15	14	22	20	10	22	22	24	28	28	25	28	29	30	31	35	35	29	62	36	37	37	43	42	43	48	43	48	48	48	36	48	51	49	48	52	53	57	57	54	57	58	62	62	35	66	66	66	62	68	62	68	7
-	-	-	-	-	PER_DESC-B	-	-	-	-	-	-	-	-	-	-	-	-	-	-	-	-	PERSON-B	-	-	-	-	-	-	-	-	PERSON-B	-	-	-	DATE-B	DATE-I	-	-	-	-	-	ORGANIZATION-B	-	-	-	-	-	-	PERSON-B	PERSON-I	-	PER_DESC-B	-	-	NATIONALITY-B	ORG_DESC-B	-	DATE-B	-	PERSON-B	-	CARDINAL-B	CARDINAL-I	-	-	-	-	-	-
</negative>
<negative>
A	high	school	dropout	who	drifted	from	job	to	job	until	he	caught	on	as	a	bank	trainee	and	rose	to	become	chancellor	of	the	exchequer	in	Margaret	Thatcher	's	Cabinet	,	Major	personifies	the	Conservative	Party	as	rebuilt	by	Thatcher	to	recognize	talent	and	reward	merit	.
DT	JJ	NN	NN	WP	VBD	IN	NN	TO	NN	IN	PRP	VBD	IN	IN	DT	NN	NN	CC	VBD	TO	VB	NN	IN	DT	NN	IN	NNP	NNP	POS	NNP	,	NNP	VBZ	DT	JJ	NNP	IN	VBN	IN	NNP	TO	VB	NN	CC	NN	NN	.
NMOD	NMOD	NMOD	SUB	NMOD	SBAR	VMOD	PMOD	VMOD	PMOD	VMOD	SUB	SBAR	VMOD	VMOD	NMOD	NMOD	PMOD	VMOD	VMOD	VMOD	VMOD	PRD	NMOD	NMOD	PMOD	NMOD	NMOD	NMOD	NMOD	PMOD	P	SUB	ROOT	NMOD	NMOD	OBJ	VMOD	SBAR	VMOD	PMOD	VMOD	VMOD	NMOD	NMOD	NMOD	OBJ	P
4	4	4	34	4	5	6	7	6	9	6	13	11	13	13	18	18	15	13	13	22	20	22	23	26	24	26	30	30	31	27	34	34	0	37	37	34	34	38	39	40	43	39	47	47	47	43	34
-	-	-	PER_DESC-B	-	-	-	-	-	-	-	-	-	-	-	-	-	-	-	-	-	-	PER_DESC-B	PER_DESC-I	PER_DESC-I	PER_DESC-I	-	PERSON-B	PERSON-I	-	ORGANIZATION-B	-	PERSON-B	-	-	ORGANIZATION-B	ORGANIZATION-I	-	-	-	PERSON-B	-	-	PER_DESC-B	-	-	-	-
</negative>
<negative>
Major	,	at	47	the	youngest	of	Britain	's	18	prime	ministers	in	this	century	,	is	himself	a	model	of	such	a	grit-and-guts	rise	out	of	poverty	.
NNP	,	IN	CD	DT	JJS	IN	NNP	POS	CD	JJ	NNS	IN	DT	NN	,	VBZ	PRP	DT	NN	IN	JJ	DT	JJ	NN	IN	IN	NN	.
SUB	P	VMOD	PMOD	NMOD	PMOD	NMOD	NMOD	NMOD	NMOD	NMOD	PMOD	NMOD	NMOD	PMOD	P	ROOT	PRD	NMOD	PRD	NMOD	NMOD	NMOD	NMOD	PMOD	NMOD	PMOD	PMOD	P
17	1	17	3	6	3	6	9	12	12	12	7	12	15	13	6	0	17	20	17	20	25	25	25	21	25	26	27	17
-	-	-	CARDINAL-B	-	-	-	GPE-B	-	CARDINAL-B	PER_DESC-B	PER_DESC-I	-	DATE-B	DATE-I	-	-	-	-	-	-	-	-	-	-	-	-	-	-
</negative>
<negative>
She	has	been	active	in	local	Huntingdon	charities	,	and	in	1987	she	published	a	biography	of	opera	singer	Joan	Sutherland	.
NNP	VBZ	VBN	JJ	IN	JJ	NNP	NNS	,	CC	IN	CD	PRP	VBD	DT	NN	IN	NN	NN	NNP	NNP	.
SUB	ROOT	VC	PRD	VMOD	NMOD	NMOD	PMOD	P	VMOD	VMOD	PMOD	SUB	VMOD	NMOD	OBJ	NMOD	NMOD	NMOD	NMOD	PMOD	P
2	0	2	3	3	8	8	5	14	14	14	11	14	3	16	14	16	21	21	21	17	2
-	-	-	-	-	-	NATIONALITY-B	ORG_DESC-B	-	-	-	DATE-B	-	-	-	-	-	-	PER_DESC-B	PERSON-B	PERSON-I	-
</negative>
<negative>
He	will	succeed	Margaret	Thatcher	as	prime	minister	.
PRP	MD	VB	NNP	NNP	IN	JJ	NN	.
SUB	ROOT	VC	NMOD	OBJ	VMOD	NMOD	PMOD	P
2	0	2	5	3	3	8	6	2
-	-	-	PERSON-B	PERSON-I	-	PER_DESC-B	PER_DESC-I	-
</negative>
<negative>
ON	THE	ECONOMY	:	In	the	mold	of	Margaret	Thatcher	,	Major	is	a	rigorous	free-marketeer	who	will	follow	her	policies	of	selling	nationalized	industries	and	holding	down	government	spending	.
NNP	NNP	NNP	:	IN	DT	NN	IN	NNP	NNP	,	NNP	VBZ	DT	JJ	JJ	WP	MD	VB	PRP$	NNS	IN	VBG	JJ	NNS	CC	VBG	RP	NN	NN	.
NMOD	NMOD	DEP	P	VMOD	NMOD	PMOD	NMOD	NMOD	PMOD	P	SUB	ROOT	NMOD	NMOD	PRD	NMOD	SBAR	VC	NMOD	OBJ	NMOD	PMOD	NMOD	OBJ	VMOD	VMOD	VMOD	NMOD	OBJ	P
3	3	5	3	13	7	5	7	10	8	13	13	0	16	16	13	16	17	18	21	19	21	22	25	23	23	23	27	30	27	13
-	-	ORGANIZATION-B	-	-	-	-	-	PERSON-B	PERSON-I	-	PERSON-B	-	-	-	PER_DESC-B	-	-	-	-	-	-	-	-	-	-	-	-	-	-	-
</negative>
</QApairs>